{
  "DIGITAL_TO_ANALOG": {
    "NAME": "Digital to analogue",
    "DESCRIPTION": "Converts a digital state to a impulse",
    "STATE_TO_IMPULS": {
      "NAME": "State to impuls",
      "DESCRIPTION": "",
      "INPUT": {
        "NAME": "State input"
      },
      "OUTPUT": {
        "NAME": "Impuls output"
      },
      "DELAY": {
        "NAME": "Impulse time [ms]"
      }
    },
    "TRIGGER": {
      "NAME": "Trigger",
      "DESCRIPTION": "",
      "INPUT": {
        "NAME": "Trigger start"
      },
      "OUTPUT": {
        "NAME": "Trigger value"
      },
      "DELAY": {
        "NAME": "Trigger delay [ms]"
      },
      "VALUE": {
        "NAME": "Trigger value"
      },
      "VALUE_PARAM": {
        "NAME": "Trigger value"
      }
    }
  }
}
