{"Automatica":{"manifest-version":{"Minor":1,"Major":0,"Build":0,"Revision":0},"plugin-version":{"Minor":9,"Major":0,"Build":0,"Revision":0},"PluginGuid":"916191e6-ccb1-4eac-aaf7-ef91697c22f9","Name":"P3.Driver.EnOcean.DriverFactory","ComponentName":"EnOcean","Type":"driver","Output":"P3.Driver.EnOcean.DriverFactory.dll","Resources":[],"Dependencies":["P3.Driver.EnOcean.dll","RJCP.SerialPortStream.dll"],"ProjectPage":"https://github.com/automatica-core/automatica.enocean","MinCoreServerVersion":{"Minor":0,"Major":5,"Build":0,"Revision":1},"MandatoryLicenseFeatures":[],"OptionalLicenseFeatures":[]}}