{
  "OPERATIONS": {
    "NAME": "Bedienung",
    "DESCRIPTION": "Bedienung",
    "SWITCH": {
      "NAME": "Schalter",
      "DESCRIPTION": "",
      "INPUT": {
        "NAME": "Status",
        "DESCRIPTION": "Eingangswert (Ein/Aus)",
        "VALUE": {
          "NAME": "Status",
          "DESCRIPTION": "Eingangswert (Ein/Aus)"
        },
        "STATE": {
          "NAME": "Wert",
          "DESCRIPTION": "Absoluter Wert (0-100%)"
        },
        "RESET": {
          "NAME": "Reset",
          "DESCRIPTION": "Reset (Setzt den Wert auf 0%)"
        }
      },
      "STATE": {
        "NAME": "Status",
        "DESCRIPTION": "S"
      },
      "OUTPUT": {
        "NAME": "Ausgang",
        "DESCRIPTION": "O"
      }
    },
    "PUSH": {
      "NAME": "Taster",
      "DESCRIPTION": "",
      "INPUT": {
        "NAME": "Eingang",
        "DESCRIPTION": "Eingangswert"
      },
      "DURATION": {
        "NAME": "Dauer",
        "DESCRIPTION": ""
      },
      "OUTPUT": {
        "NAME": "Ausgang",
        "DESCRIPTION": "O"
      }
    },
    "DIMMER": {
      "NAME": "Dimmer",
      "DESCRIPTION": "Dimmer",
      "INPUT": {
        "STATE": {
          "NAME": "State",
          "DESCRIPTION": "S"
        },
        "RESET": {
          "NAME": "Reset",
          "DESCRIPTION": "R"
        },
        "VALUE": {
          "NAME": "Value",
          "Description": "Dimm Value"
        }
      },
      "OUTPUT": {
        "VALUE": {
          "NAME": "Value",
          "DESCRIPTION": "V"
        },
        "STATE": {
          "NAME": "State",
          "DESCRIPTION": "S"
        }
      }
    },
    "SLIDER": {
      "NAME": "Slider",
      "DESCRIPTION": "Slider",
      "INPUT": {
        "STATE": {
          "NAME": "State",
          "DESCRIPTION": "S"
        },
        "RESET": {
          "NAME": "Reset",
          "DESCRIPTION": "R"
        },
        "VALUE": {
          "NAME": "Value",
          "Description": "Value"
        },
        "VALUE_MIN": {
          "NAME": "VMIN",
          "Description": "Min Value"
        },
        "VALUE_MAX": {
          "NAME": "VMAX",
          "Description": "Max Value"
        }
      },
      "OUTPUT": {
        "VALUE": {
          "NAME": "Value",
          "DESCRIPTION": "V"
        },
        "STATE": {
          "NAME": "State",
          "DESCRIPTION": "V > 0"
        }
      }
    },
    "GAUGE": {
      "EASY_LINEAR": {
        "NAME": "Linear (1 Scale)",
        "DESCRIPTION": ""
      },
      "EASY_CIRCULAR": {
        "NAME": "Circular (1 Scale)",
        "DESCRIPTION": ""
      },
      "RANGE_CIRCULAR": {
        "NAME": "Circular (3 Scale)",
        "DESCRIPTION": ""
      },
      "SCALE_START": {
        "NAME": "Scale start",
        "DESCRIPTION": ""
      },
      "SCALE_END": {
        "NAME": "Scale end",
        "DESCRIPTION": ""
      },
      "FIRST_SCALE_START": {
        "NAME": "First Scale start",
        "DESCRIPTION": ""
      },
      "FIRST_SCALE_END": {
        "NAME": "First Scale end",
        "DESCRIPTION": ""
      },
      "FIRST_COLOR": {
        "NAME": "First color",
        "DESCRIPTION": ""
      },
      "SECOND_SCALE_START": {
        "NAME": "Second Scale start",
        "DESCRIPTION": ""
      },
      "SECOND_SCALE_END": {
        "NAME": "Second Scale end",
        "DESCRIPTION": ""
      },
      "SECOND_COLOR": {
        "NAME": "Second color",
        "DESCRIPTION": ""
      },
      "THIRD_SCALE_START": {
        "NAME": "Third Scale start",
        "DESCRIPTION": ""
      },
      "THIRD_SCALE_END": {
        "NAME": "ThirdScale end",
        "DESCRIPTION": ""
      },
      "THIRD_COLOR": {
        "NAME": "Third color",
        "DESCRIPTION": ""
      },
      "TICKS": {
        "NAME": "Ticks",
        "DESCRIPTION": ""
      },
      "TYPE": {
        "NAME": "Type",
        "DESCRIPTION": ""
      },
      "VALUE": {
        "NAME": "Value",
        "Description": "Value"
      }
    },
    "SHUTTER": {
      "NAME": "Shutter",
      "DESCRIPTION": "Shutter",
      "INPUT": {
        "MOVE": {
          "NAME": "Move",
          "DESCRIPTION": ""
        },
        "DIRECTION": {
          "NAME": "Direction",
          "DESCRIPTION": ""
        },
        "UP": {
          "NAME": "Up",
          "DESCRIPTION": ""
        },
        "DOWN": {
          "NAME": "Down",
          "DESCRIPTION": ""
        },
        "STOP": {
          "NAME": "Stop",
          "DESCRIPTION": ""
        },
        "ABSOLUTE": {
          "NAME": "Position",
          "DESCRIPTION": ""
        },
        "LOCKED": {
          "NAME": "Gesperrt",
          "DESCRIPTION": ""
        }
      },
      "OUTPUT": {
        "MOVE": {
          "NAME": "Move",
          "DESCRIPTION": ""
        },
        "ABSOLUTE": {
          "NAME": "Position",
          "DESCRIPTION": ""
        },
        "DIRECTION": {
          "NAME": "Direction",
          "DESCRIPTION": ""
        },
        "STOP": {
          "NAME": "Stop",
          "DESCRIPTION": ""
        },
        "IS_MOVING": {
          "NAME": "Is Moving"
        }
      }
    }
  }
}
